wayback_recon/__init__.py
wayback_recon/pattern_config.json
wayback_recon/wayback_recon.py
wayback_recon-0.2.3.dist-info/METADATA
wayback_recon-0.2.3.dist-info/WHEEL
wayback_recon-0.2.3.dist-info/entry_points.txt
wayback_recon-0.2.3.dist-info/RECORD
